odoo_configurator/__init__.py
odoo_configurator/__main__.py
odoo_configurator/bitwarden.py
odoo_configurator/configurator.py
odoo_configurator/import_manager.py
odoo_configurator/keepass.py
odoo_configurator/logging.py
odoo_configurator/odoo_connection.py
odoo_configurator/sql.py
odoo_configurator/utils.py
odoo_configurator/apps/__init__.py
odoo_configurator/apps/account.py
odoo_configurator/apps/base.py
odoo_configurator/apps/call.py
odoo_configurator/apps/config.py
odoo_configurator/apps/connection.py
odoo_configurator/apps/datas.py
odoo_configurator/apps/defaults.py
odoo_configurator/apps/import_configurator.py
odoo_configurator/apps/imports.py
odoo_configurator/apps/mattermost.py
odoo_configurator/apps/modules.py
odoo_configurator/apps/python_script.py
odoo_configurator/apps/roles.py
odoo_configurator/apps/slack.py
odoo_configurator/apps/system_parameter.py
odoo_configurator/apps/translations.py
odoo_configurator/apps/users.py
odoo_configurator/apps/website.py
odoo_configurator-3.7.7.dist-info/licenses/LICENSE
templates/0_base.yml
templates/1_base_auto_entreprise.yml
templates/1_base_entreprise.yml
templates/2_base_account.yml
templates/2_base_account_14.yml
templates/2_base_account_entreprise.yml
templates/2_base_crm.yml
templates/2_base_event.yml
templates/2_base_expense.yml
templates/2_base_ged.yml
templates/2_base_hr.yml
templates/2_base_maintenance.yml
templates/2_base_marketing.yml
templates/2_base_mrp.yml
templates/2_base_purchase.yml
templates/2_base_sale.yml
templates/2_base_sale_subscription.yml
templates/2_base_sign.yml
templates/2_base_website.yml
templates/14.0/0_base.yml
odoo_configurator-3.7.7.dist-info/METADATA
odoo_configurator-3.7.7.dist-info/WHEEL
odoo_configurator-3.7.7.dist-info/entry_points.txt
odoo_configurator-3.7.7.dist-info/top_level.txt
odoo_configurator-3.7.7.dist-info/RECORD
