Metadata-Version: 2.4
Name: odoo-configurator
Version: 3.7.7
Summary: Configure and update Odoo database with YAML files
Author-email: Michel Perrocheau <myrrkel@gmail.com>, David Halgand <david@scalizer.fr>
License:                    GNU LESSER GENERAL PUBLIC LICENSE
Project-URL: Homepage, https://github.com/ScalizerOrg/odoo-configurator
Project-URL: Changelog, https://github.com/ScalizerOrg/odoo-configurator/blob/main/CHANGELOG.md
Keywords: odoo,configurator,xmlrpc,yaml
Classifier: License :: OSI Approved :: GNU Lesser General Public License v3 (LGPLv3)
Classifier: Programming Language :: Python
Classifier: Programming Language :: Python :: 3
Classifier: Framework :: Odoo
Requires-Python: >=3.9
License-File: LICENSE
Requires-Dist: beautifulsoup4
Requires-Dist: HiYaPyCo
Requires-Dist: pykeepass
Requires-Dist: cryptocode
Requires-Dist: s6r_bitwarden_cli
Requires-Dist: s6r-odoo
Requires-Dist: psycopg
Requires-Dist: pymssql
Requires-Dist: requests
Requires-Dist: unidecode
Requires-Dist: pyodbc
Requires-Dist: mysql-connector-python
Requires-Dist: slack_sdk
Requires-Dist: toml
Requires-Dist: packaging
Provides-Extra: dev
Requires-Dist: twine; extra == "dev"
Requires-Dist: bumpver; extra == "dev"
Requires-Dist: pip-tools; extra == "dev"
Requires-Dist: pytest; extra == "dev"
Requires-Dist: check-manifest; extra == "dev"
Dynamic: license-file
